README.txt
setup.cfg
setup.py
Products/__init__.py
Products.PASIPAuth.egg-info/PKG-INFO
Products.PASIPAuth.egg-info/SOURCES.txt
Products.PASIPAuth.egg-info/dependency_links.txt
Products.PASIPAuth.egg-info/namespace_packages.txt
Products.PASIPAuth.egg-info/top_level.txt
Products/PASIPAuth/AuthIPPlugin.py
Products/PASIPAuth/__init__.py
Products/PASIPAuth/cidr.py
Products/PASIPAuth/configure.zcml
Products/PASIPAuth/version.txt
Products/PASIPAuth/www/PluggableAuthService.png
Products/PASIPAuth/www/ipAuthAdd.zpt