Metadata-Version: 1.0
Name: Products.PASIPAuth
Version: 0.2
Summary: PAS plugin that authenticates by ip address
Home-page: http://www.upfrontsystems.co.za/
Author: Izak Burger
Author-email: izak@upfrontsystems.co.za
License: GPL
Platform: UNKNOWN
Classifier: Framework :: Plone
Classifier: Framework :: Zope2
Classifier: Programming Language :: Python
Classifier: Intended Audience :: System Administrators
Classifier: Topic :: System :: Systems Administration :: Authentication/Directory
Classifier: Topic :: Software Development :: Libraries :: Python Modules
